elastic_tables/__init__.py
elastic_tables/io.py
elastic_tables/cli/cli.py
elastic_tables/filter/__init__.py
elastic_tables/filter/filter.py
elastic_tables/filter/stream_filter.py
elastic_tables/model/__init__.py
elastic_tables/model/block.py
elastic_tables/model/cell.py
elastic_tables/model/column.py
elastic_tables/model/line.py
elastic_tables/model/row.py
elastic_tables/model/table.py
elastic_tables/parsing/__init__.py
elastic_tables/parsing/block_splitter.py
elastic_tables/parsing/line_splitter.py
elastic_tables/util/__init__.py
elastic_tables/util/alignment.py
elastic_tables/util/iterable.py
elastic_tables/util/text.py
elastic_tables-0.0.3.dist-info/entry_points.txt
elastic_tables-0.0.3.dist-info/LICENSE
elastic_tables-0.0.3.dist-info/WHEEL
elastic_tables-0.0.3.dist-info/METADATA
elastic_tables-0.0.3.dist-info/RECORD
